checkio_client/__init__.py
checkio_client/api.py
checkio_client/eoc_runner.py
checkio_client/runner.py
checkio_client/settings.py
checkio_client/web_plugin.py
checkio_client/actions/__init__.py
checkio_client/actions/autofill.py
checkio_client/actions/available.py
checkio_client/actions/check.py
checkio_client/actions/config.py
checkio_client/actions/eoc.py
checkio_client/actions/init.py
checkio_client/actions/open.py
checkio_client/actions/plugin.py
checkio_client/actions/repo.py
checkio_client/actions/repo_check.py
checkio_client/actions/repo_convert.py
checkio_client/actions/server.py
checkio_client/actions/sync.py
checkio_client/actions/system.py
checkio_client/eoc/__init__.py
checkio_client/eoc/folder.py
checkio_client/eoc/getters.py
checkio_client/eoc/initial.py
checkio_client/eoc/settings.py
checkio_client/eoc/testing.py
checkio_client/utils/__init__.py
checkio_client/utils/code.py
checkio_client/verification/__init__.py
checkio_client/verification/echo.py
checkio_client/verification/uch.py
checkio_client/verification/checkio/__init__.py
checkio_client/verification/checkio/api.py
checkio_client/verification/checkio/code_template.py
checkio_client/verification/checkio/runner_types.py
checkio_client/verification/checkio/signals.py
checkio_client/verification/checkio/utils.py
checkio_client/verification/checkio/referees/__init__.py
checkio_client/verification/checkio/referees/checkers.py
checkio_client/verification/checkio/referees/code.py
checkio_client/verification/checkio/referees/cover_codes.py
checkio_client/verification/checkio/referees/inspectors.py
checkio_client/verification/checkio/referees/io.py
checkio_client/verification/checkio/referees/io_template.py
checkio_client/verification/checkio/referees/multicall.py
checkio_client-0.3.4.dist-info/LICENSE
checkio_client-0.3.4.dist-info/METADATA
checkio_client-0.3.4.dist-info/WHEEL
checkio_client-0.3.4.dist-info/entry_points.txt
checkio_client-0.3.4.dist-info/top_level.txt
checkio_client-0.3.4.dist-info/RECORD
