Metadata-Version: 2.1
Name: checkio-client
Version: 0.3.4
Summary: Command line interface for playing CheckiO games
Home-page: https://github.com/CheckiO/checkio-client
Author: CheckiO
Author-email: a.lyabah@checkio.org
License: UNKNOWN
Platform: UNKNOWN
Classifier: Programming Language :: Python :: 3
Classifier: License :: OSI Approved :: MIT License
Classifier: Operating System :: OS Independent
Requires-Python: >=3.8
License-File: LICENSE
Requires-Dist: Exscript (==2.6.28)
Requires-Dist: websockets (==10.3)
Requires-Dist: requests (==2.31.0)
Requires-Dist: aiohttp (==3.9.5)
Requires-Dist: aiohttp-cors (==0.7.0)
Requires-Dist: python-daemon (==2.3.0)
Requires-Dist: pid (==3.0.4)
Requires-Dist: checkio-json-serializer (==0.2.3)
